LICENSE
MANIFEST.in
README.rst
setup.py
discounts_cart/__init__.py
discounts_cart/admin.py
discounts_cart/apps.py
discounts_cart/context_processors.py
discounts_cart/models.py
discounts_cart/tests.py
discounts_cart/urls.py
discounts_cart/utils.py
discounts_cart/views.py
discounts_cart/locale/ru/LC_MESSAGES/django.mo
discounts_cart/locale/ru/LC_MESSAGES/django.po
discounts_cart/management/__init__.py
discounts_cart/management/commands/__init__.py
discounts_cart/management/commands/discounts_cart.py
discounts_cart/migrations/0001_initial.py
discounts_cart/migrations/__init__.py
discounts_cart/templatetags/__init__.py
discounts_cart/templatetags/discounts_cart.py
django_discounts_cart.egg-info/PKG-INFO
django_discounts_cart.egg-info/SOURCES.txt
django_discounts_cart.egg-info/dependency_links.txt
django_discounts_cart.egg-info/top_level.txt