Metadata-Version: 1.1
Name: django-discounts-cart
Version: 1.1.7
Summary: Discounts for online store and management cart
Home-page: https://github.com/genkosta/django-discounts-cart
Author: genkosta
Author-email: genkosta43@gmail.com
License: MIT License
Download-URL: https://github.com/genkosta/django-discounts-cart/tarball/master
Keywords: django discounts cart commerce e-ecommerce
Platform: UNKNOWN
Classifier: Environment :: Web Environment
Classifier: Framework :: Django
Classifier: Intended Audience :: Developers
Classifier: Programming Language :: Python
Classifier: Programming Language :: Python
Classifier: Programming Language :: Python :: 2
Classifier: Programming Language :: Python :: 2.7
Requires: python (== 2.7)
Requires: django (>= 1.7)
